datapac/__init__.py
datapac/cli.py
datapac/config.py
datapac/logging.py
datapac/package/__init__.py
datapac/package/artefact.py
datapac/package/package.py
datapac/package/path.py
datapac/rcave/__init__.py
datapac/rcave/cli.py
datapac/rcave/services/__init__.py
datapac/rcave/services/pull.py
datapac/rcave/services/push.py
datapac/rcave/sources/__init__.py
datapac/rcave/sources/postgres/__init__.py
datapac/rcave/sources/postgres/client.py
datapac/rcave/sources/postgres/source.py
datapac/rcave/sources/s3/__init__.py
datapac/rcave/sources/s3/client.py
datapac/rcave/sources/s3/source.py
datapac/rcave/utils/__init__.py
datapac/rcave/utils/query.py
datapac/utils/__init__.py
datapac/utils/json.py
datapac/utils/templating.py
datapac-0.1.5.dist-info/entry_points.txt
datapac-0.1.5.dist-info/LICENSE.md
datapac-0.1.5.dist-info/WHEEL
datapac-0.1.5.dist-info/METADATA
datapac-0.1.5.dist-info/RECORD
