Metadata-Version: 2.1
Name: datapac
Version: 0.1.5
Summary: 
Author: Jerguš Lejko
Author-email: jergus.lejko@gmail.com
Requires-Python: >=3.10,<4.0
Classifier: Programming Language :: Python :: 3
Classifier: Programming Language :: Python :: 3.10
Classifier: Programming Language :: Python :: 3.11
Requires-Dist: Jinja2 (>=3.1.2,<4.0.0)
Requires-Dist: PyYAML (>=6.0,<7.0)
Requires-Dist: boto3 (>=1.24.81,<2.0.0)
Requires-Dist: click (>=8.1.3,<9.0.0)
Requires-Dist: psycopg2 (>=2.9.3,<3.0.0)
Requires-Dist: pydantic (>=1.10.2,<2.0.0)
Requires-Dist: toml (>=0.10.2,<0.11.0)
